setup.py
personal_assistant_bot_pyoneers/main.py
personal_assistant_bot_pyoneers.egg-info/PKG-INFO
personal_assistant_bot_pyoneers.egg-info/SOURCES.txt
personal_assistant_bot_pyoneers.egg-info/dependency_links.txt
personal_assistant_bot_pyoneers.egg-info/entry_points.txt
personal_assistant_bot_pyoneers.egg-info/requires.txt
personal_assistant_bot_pyoneers.egg-info/top_level.txt
personal_assistant_bot_pyoneers/src/__init__.py
personal_assistant_bot_pyoneers/src/autocompletion.py
personal_assistant_bot_pyoneers/src/decorators.py
personal_assistant_bot_pyoneers/src/helpers.py
personal_assistant_bot_pyoneers/src/serializers.py
personal_assistant_bot_pyoneers/src/types.py
personal_assistant_bot_pyoneers/src/classes/__init__.py
personal_assistant_bot_pyoneers/src/classes/address_book.py
personal_assistant_bot_pyoneers/src/classes/bot_menu.py
personal_assistant_bot_pyoneers/src/classes/custom_errors.py
personal_assistant_bot_pyoneers/src/classes/note.py
personal_assistant_bot_pyoneers/src/classes/note_book.py
personal_assistant_bot_pyoneers/src/classes/record.py
personal_assistant_bot_pyoneers/src/classes/table_formatted.py
personal_assistant_bot_pyoneers/src/classes/upcoming_birthday.py
personal_assistant_bot_pyoneers/src/classes/fields/__init__.py
personal_assistant_bot_pyoneers/src/classes/fields/address.py
personal_assistant_bot_pyoneers/src/classes/fields/birthday.py
personal_assistant_bot_pyoneers/src/classes/fields/description.py
personal_assistant_bot_pyoneers/src/classes/fields/email.py
personal_assistant_bot_pyoneers/src/classes/fields/field.py
personal_assistant_bot_pyoneers/src/classes/fields/name.py
personal_assistant_bot_pyoneers/src/classes/fields/phone.py
personal_assistant_bot_pyoneers/src/classes/fields/tag.py
personal_assistant_bot_pyoneers/src/commands/contact_commands.py
personal_assistant_bot_pyoneers/src/commands/exit_commands.py
personal_assistant_bot_pyoneers/src/commands/help_commands.py
personal_assistant_bot_pyoneers/src/commands/notebook_commands.py
personal_assistant_bot_pyoneers/src/handlers/contact_handlers.py
personal_assistant_bot_pyoneers/src/handlers/helpers.py
personal_assistant_bot_pyoneers/src/handlers/notebook_handlers.py
personal_assistant_bot_pyoneers/src/output/pretty_output.py
personal_assistant_bot_pyoneers/src/output/table_output.py