Metadata-Version: 2.1
Name: personal_assistant_bot_pyoneers
Version: 2
Summary: A DEMO version of Personal Assistant Bot.
Home-page: https://github.com/SergeyPoly/goit-pycore-final-project.git
Author: PyOneers-team
Author-email: spoly82@gmail.com
License: MIT
Classifier: Programming Language :: Python :: 3
Requires-Dist: prompt_toolkit
Requires-Dist: prettytable
Requires-Dist: colorama
Requires-Dist: wcwidth
